<?xml version="1.0" encoding="utf-8" ?>
<dwsync>
<file name="blue.css" server="107.180.56.173/public_html/" local="130391463640000000" remote="131984564400000000" Dst="2" />
<file name="cyan.css" server="107.180.56.173/public_html/" local="130391463640000000" remote="131984564400000000" Dst="2" />
<file name="empty.css" server="107.180.56.173/public_html/" local="130391463640000000" remote="131984564400000000" Dst="2" />
<file name="green.css" server="107.180.56.173/public_html/" local="130393288100000000" remote="131984564400000000" Dst="2" />
<file name="grunge.css" server="107.180.56.173/public_html/" local="130391463640000000" remote="131984564400000000" Dst="2" />
<file name="light_blue.css" server="107.180.56.173/public_html/" local="130391463640000000" remote="131984564400000000" Dst="2" />
<file name="light_green.css" server="107.180.56.173/public_html/" local="130393294300000000" remote="131984564400000000" Dst="2" />
<file name="lime.css" server="107.180.56.173/public_html/" local="130391463640000000" remote="131984564400000000" Dst="2" />
<file name="navy.css" server="107.180.56.173/public_html/" local="130391463640000000" remote="131984564400000000" Dst="2" />
<file name="orange.css" server="107.180.56.173/public_html/" local="130391463640000000" remote="131984564400000000" Dst="2" />
<file name="pink.css" server="107.180.56.173/public_html/" local="130391463640000000" remote="131984564400000000" Dst="2" />
<file name="purple.css" server="107.180.56.173/public_html/" local="130391463640000000" remote="131984564400000000" Dst="2" />
<file name="red.css" server="107.180.56.173/public_html/" local="130391463640000000" remote="131984564400000000" Dst="2" />
</dwsync>